simple_factorial/__init__.py
simple_factorial-0.0.2.dist-info/LICENSE
simple_factorial-0.0.2.dist-info/METADATA
simple_factorial-0.0.2.dist-info/WHEEL
simple_factorial-0.0.2.dist-info/top_level.txt
simple_factorial-0.0.2.dist-info/RECORD
