Metadata-Version: 2.1
Name: simple-factorial
Version: 0.0.2
Summary: A simple Python module designed to calculate the factorial of a non-negative integer.
Author-email: Rufus Gordon-Heywood <rufus.gordonheywood@education.nsw.gov.au>
Project-URL: Homepage, https://github.com/google-docs-shorturl/factorial
Project-URL: Bug Tracker, https://github.com/google-docs-shorturl/factorial/issues
Classifier: Programming Language :: Python :: 3
Classifier: License :: OSI Approved :: MIT License
Classifier: Operating System :: OS Independent
Requires-Python: >=3.5
License-File: LICENSE
